{"id1":"sujins2@illinois.edu_1_01_mps","id2":"sc107@illinois.edu_1_01_mps","similarity":0.9021479713603818,"matches":[{"file1":"sujins2@illinois.edu_1_01_mps\\mp_stickers_1_1_90732199_StickerSheet.cpp","file2":"sc107@illinois.edu_1_01_mps\\mp_stickers_1_3_90732875_StickerSheet.cpp","start1":22,"end1":115,"start2":44,"end2":134,"tokens":107},{"file1":"sujins2@illinois.edu_1_01_mps\\mp_stickers_1_1_90732199_Image.cpp","file2":"sc107@illinois.edu_1_01_mps\\mp_stickers_1_3_90732875_Image.cpp","start1":115,"end1":170,"start2":145,"end2":201,"tokens":82},{"file1":"sujins2@illinois.edu_1_01_mps\\mp_stickers_1_1_90732199_Image.cpp","file2":"sc107@illinois.edu_1_01_mps\\mp_stickers_1_3_90732875_Image.cpp","start1":44,"end1":67,"start2":56,"end2":78,"tokens":48},{"file1":"sujins2@illinois.edu_1_01_mps\\mp_stickers_1_1_90732199_StickerSheet.h","file2":"sc107@illinois.edu_1_01_mps\\mp_stickers_1_3_90732875_StickerSheet.h","start1":9,"end1":33,"start2":8,"end2":34,"tokens":37},{"file1":"sujins2@illinois.edu_1_01_mps\\mp_stickers_1_1_90732199_StickerSheet.cpp","file2":"sc107@illinois.edu_1_01_mps\\mp_stickers_1_3_90732875_StickerSheet.cpp","start1":148,"end1":175,"start2":163,"end2":193,"tokens":31},{"file1":"sujins2@illinois.edu_1_01_mps\\mp_stickers_1_1_90732199_StickerSheet.cpp","file2":"sc107@illinois.edu_1_01_mps\\mp_stickers_1_3_90732875_StickerSheet.cpp","start1":177,"end1":196,"start2":17,"end2":36,"tokens":30},{"file1":"sujins2@illinois.edu_1_01_mps\\mp_stickers_1_1_90732199_Image.h","file2":"sc107@illinois.edu_1_01_mps\\mp_stickers_1_3_90732875_Image.h","start1":19,"end1":39,"start2":17,"end2":31,"tokens":22},{"file1":"sujins2@illinois.edu_1_01_mps\\mp_stickers_1_1_90732199_Image.cpp","file2":"sc107@illinois.edu_1_01_mps\\mp_stickers_1_3_90732875_Image.cpp","start1":94,"end1":105,"start2":30,"end2":41,"tokens":20},{"file1":"sujins2@illinois.edu_1_01_mps\\mp_stickers_1_1_90732199_Image.cpp","file2":"sc107@illinois.edu_1_01_mps\\mp_stickers_1_3_90732875_Image.cpp","start1":16,"end1":24,"start2":20,"end2":29,"tokens":19},{"file1":"sujins2@illinois.edu_1_01_mps\\mp_stickers_1_1_90732199_Image.cpp","file2":"sc107@illinois.edu_1_01_mps\\mp_stickers_1_3_90732875_Image.cpp","start1":35,"end1":43,"start2":44,"end2":53,"tokens":19},{"file1":"sujins2@illinois.edu_1_01_mps\\mp_stickers_1_1_90732199_Image.cpp","file2":"sc107@illinois.edu_1_01_mps\\mp_stickers_1_3_90732875_Image.cpp","start1":70,"end1":78,"start2":133,"end2":142,"tokens":19},{"file1":"sujins2@illinois.edu_1_01_mps\\mp_stickers_1_1_90732199_Image.cpp","file2":"sc107@illinois.edu_1_01_mps\\mp_stickers_1_3_90732875_Image.cpp","start1":25,"end1":34,"start2":121,"end2":130,"tokens":18},{"file1":"sujins2@illinois.edu_1_01_mps\\mp_stickers_1_1_90732199_Image.cpp","file2":"sc107@illinois.edu_1_01_mps\\mp_stickers_1_3_90732875_Image.cpp","start1":79,"end1":86,"start2":99,"end2":106,"tokens":18},{"file1":"sujins2@illinois.edu_1_01_mps\\mp_stickers_1_1_90732199_StickerSheet.cpp","file2":"sc107@illinois.edu_1_01_mps\\mp_stickers_1_3_90732875_StickerSheet.cpp","start1":3,"end1":14,"start2":3,"end2":15,"tokens":18},{"file1":"sujins2@illinois.edu_1_01_mps\\mp_stickers_1_1_90732199_Image.cpp","file2":"sc107@illinois.edu_1_01_mps\\mp_stickers_1_3_90732875_Image.cpp","start1":6,"end1":15,"start2":7,"end2":17,"tokens":17},{"file1":"sujins2@illinois.edu_1_01_mps\\mp_stickers_1_1_90732199_Image.cpp","file2":"sc107@illinois.edu_1_01_mps\\mp_stickers_1_3_90732875_Image.cpp","start1":106,"end1":112,"start2":85,"end2":92,"tokens":17},{"file1":"sujins2@illinois.edu_1_01_mps\\mp_stickers_1_1_90732199_StickerSheet.cpp","file2":"sc107@illinois.edu_1_01_mps\\mp_stickers_1_3_90732875_StickerSheet.cpp","start1":136,"end1":145,"start2":153,"end2":161,"tokens":16},{"file1":"sujins2@illinois.edu_1_01_mps\\mp_stickers_1_1_90732199_StickerSheet.cpp","file2":"sc107@illinois.edu_1_01_mps\\mp_stickers_1_3_90732875_StickerSheet.cpp","start1":127,"end1":133,"start2":144,"end2":151,"tokens":15},{"file1":"sujins2@illinois.edu_1_01_mps\\mp_stickers_1_1_90732199_StickerSheet.cpp","file2":"sc107@illinois.edu_1_01_mps\\mp_stickers_1_3_90732875_StickerSheet.cpp","start1":116,"end1":124,"start2":136,"end2":142,"tokens":14}]}